sphinx_tsn_theme/__init__.py
sphinx_tsn_theme/footer.html
sphinx_tsn_theme/layout.html
sphinx_tsn_theme/searchbox.html
sphinx_tsn_theme/theme.conf
sphinx_tsn_theme/versions.html
sphinx_tsn_theme/static/css/tiac.css
sphinx_tsn_theme/static/images/dropdown.svg
sphinx_tsn_theme/static/images/favicon.ico
sphinx_tsn_theme/static/images/tiac.svg
sphinx_tsn_theme/static/js/tiac.js_t
sphinx_tsn_theme-2024.11.0.dist-info/entry_points.txt
sphinx_tsn_theme-2024.11.0.dist-info/LICENSE
sphinx_tsn_theme-2024.11.0.dist-info/WHEEL
sphinx_tsn_theme-2024.11.0.dist-info/METADATA
sphinx_tsn_theme-2024.11.0.dist-info/RECORD
