Metadata-Version: 2.3
Name: sphinx-tsn-theme
Version: 2024.11.0
Summary: TiaC Systems Network (TSN) theme for Sphinx
Keywords: sphinx,theme,TiaC Systems Network,tiac,tiacsys,tsn
Author-email: Stephan Linz <linz@li-pro.net>, Sarah Renkhoff <sarah.renkhoff@navimatix.de>, Tobias Kästner <tobias.kaestner.jena@gmail.com>
Maintainer-email: Stephan Linz <linz@li-pro.net>, TiaC Systems Network <info@tiac-systems.net>
Requires-Python: >=3.9
Classifier: Development Status :: 5 - Production/Stable
Classifier: Environment :: Console
Classifier: Environment :: Web Environment
Classifier: Framework :: Sphinx
Classifier: Framework :: Sphinx :: Theme
Classifier: Intended Audience :: Developers
Classifier: Intended Audience :: Science/Research
Classifier: License :: OSI Approved
Classifier: License :: OSI Approved :: MIT License
Classifier: Natural Language :: English
Classifier: Operating System :: OS Independent
Classifier: Programming Language :: Python :: 3
Classifier: Programming Language :: Python :: 3 :: Only
Classifier: Programming Language :: Python :: 3.9
Classifier: Programming Language :: Python :: 3.10
Classifier: Programming Language :: Python :: 3.11
Classifier: Programming Language :: Python :: 3.12
Classifier: Programming Language :: Python :: 3.13
Classifier: Programming Language :: Python :: Implementation
Classifier: Programming Language :: Python :: Implementation :: CPython
Classifier: Programming Language :: Python :: Implementation :: PyPy
Classifier: Topic :: Documentation
Classifier: Topic :: Documentation :: Sphinx
Classifier: Topic :: Software Development
Classifier: Topic :: Software Development :: Documentation
Classifier: Topic :: Text Processing
Classifier: Topic :: Text Processing :: Markup
Classifier: Topic :: Text Processing :: Markup :: HTML
Requires-Dist: sphinx-rtd-theme>=3.0
Project-URL: Changelog, https://github.com/tiacsys/sphinx-tsn-theme/releases
Project-URL: Documentation, https://github.com/tiacsys/sphinx-tsn-theme#readme-ov-file
Project-URL: Download, https://pypi.org/project/sphinx-tsn-theme/
Project-URL: GitHub, https://github.com/tiacsys/sphinx-tsn-theme
Project-URL: Homepage, https://www.tiac-systems.net/
Project-URL: Issues, https://github.com/tiacsys/sphinx-tsn-theme/issues
Project-URL: Repository, https://github.com/tiacsys/sphinx-tsn-theme.git
